MANIFEST.in
README.txt
fsd.cmfbibliographyat-configure.zcml
setup.cfg
setup.py
docs/HISTORY.txt
docs/INSTALL.txt
docs/LICENSE.GPL
docs/LICENSE.txt
fsd/__init__.py
fsd.cmfbibliographyat.egg-info/PKG-INFO
fsd.cmfbibliographyat.egg-info/SOURCES.txt
fsd.cmfbibliographyat.egg-info/dependency_links.txt
fsd.cmfbibliographyat.egg-info/entry_points.txt
fsd.cmfbibliographyat.egg-info/namespace_packages.txt
fsd.cmfbibliographyat.egg-info/not-zip-safe
fsd.cmfbibliographyat.egg-info/requires.txt
fsd.cmfbibliographyat.egg-info/top_level.txt
fsd/cmfbibliographyat/__init__.py
fsd/cmfbibliographyat/configure.zcml
fsd/cmfbibliographyat/profiles.zcml
fsd/cmfbibliographyat/setuphandlers.py
fsd/cmfbibliographyat/skins.zcml
fsd/cmfbibliographyat/tests.py
fsd/cmfbibliographyat/version.txt
fsd/cmfbibliographyat/Extensions/Install.py
fsd/cmfbibliographyat/browser/__init__.py
fsd/cmfbibliographyat/browser/configure.zcml
fsd/cmfbibliographyat/browser/interfaces.py
fsd/cmfbibliographyat/browser/viewlet.pt
fsd/cmfbibliographyat/browser/viewlets.py
fsd/cmfbibliographyat/browser/images/README.txt
fsd/cmfbibliographyat/browser/stylesheets/README.txt
fsd/cmfbibliographyat/browser/stylesheets/main.css
fsd/cmfbibliographyat/profiles/default/cssregistry.xml
fsd/cmfbibliographyat/profiles/default/fsd.cmfbibliographyat_various.txt
fsd/cmfbibliographyat/profiles/default/import_steps.xml
fsd/cmfbibliographyat/profiles/default/jsregistry.xml
fsd/cmfbibliographyat/profiles/default/metadata.xml
fsd/cmfbibliographyat/profiles/default/skins.xml
fsd/cmfbibliographyat/profiles/default/types.xml
fsd/cmfbibliographyat/profiles/default/viewlets.xml
fsd/cmfbibliographyat/profiles/default/types/BibliographyFolder.xml
fsd/cmfbibliographyat/profiles/default/types/FSDFacultyStaffDirectory.xml
fsd/cmfbibliographyat/profiles/default/types/FSDPerson.xml
fsd/cmfbibliographyat/skins/fsd_cmfbibliographyat_custom_templates/CONTENT.txt
fsd/cmfbibliographyat/skins/fsd_cmfbibliographyat_custom_templates/person_publications.py
fsd/cmfbibliographyat/skins/fsd_cmfbibliographyat_custom_templates/person_publications_macros.pt
fsd/cmfbibliographyat/skins/fsd_cmfbibliographyat_custom_templates/person_publications_view.pt
fsd/cmfbibliographyat/skins/fsd_cmfbibliographyat_custom_templates/person_publications_view.pt.metadata
