Metadata-Version: 1.0
Name: fsd.cmfbibliographyat
Version: 0.2.0
Summary: A simple integration of CMFBibliographyAT with FacultyStaffDirectory
Home-page: https://weblion.psu.edu/svn/weblion/weblion/fsd.cmfbibliographyat/trunk/fsd/cmfbibliographyat
Author: Andreas Jung
Author-email: info@zopyx.com
License: ZPL
Keywords: web zope plone theme
Platform: UNKNOWN
Classifier: Framework :: Plone
Classifier: Programming Language :: Python
Classifier: Topic :: Software Development :: Libraries :: Python Modules
